psycossh/__init__.py
psycossh-0.0.1.dist-info/LICENSE
psycossh-0.0.1.dist-info/METADATA
psycossh-0.0.1.dist-info/WHEEL
psycossh-0.0.1.dist-info/top_level.txt
psycossh-0.0.1.dist-info/RECORD
