Metadata-Version: 2.1
Name: psycossh
Version: 0.0.1
Summary: A ConnectionFactory for use by psycopg2 to enable SSH Tunneling
Home-page: https://github.com/mpca-adau/psycossh
Author: Daniel Sullivan
Author-email: daniel.sullivan@state.mn.us
License: LGPL-3.0
Platform: UNKNOWN
Classifier: Programming Language :: Python :: 2.7
Classifier: Programming Language :: Python :: 3
Classifier: License :: OSI Approved :: GNU Lesser General Public License v3 (LGPLv3)
Requires-Dist: sshtunnel
Requires-Dist: psycopg2
Requires-Dist: sqlalchemy
